LICENSE
README.md
deciml/__init__.py
deciml/deciml.py
deciml-0.2.3.dist-info/METADATA
deciml-0.2.3.dist-info/WHEEL
deciml-0.2.3.dist-info/licenses/LICENSE
deciml-0.2.3.dist-info/RECORD
