Metadata-Version: 2.4
Name: deciml
Version: 0.2.3
Summary: Extension of decimal library.
Project-URL: Homepage, https://github.com/putterPatcher/deciml
Project-URL: Issues, https://github.com/putterPatcher/deciml/issues
Author-email: Kor Shantanu Nitin <korshantanu@gmail.com>
License: MIT
License-File: LICENSE
Classifier: Operating System :: OS Independent
Classifier: Programming Language :: Python :: 3
Requires-Python: >=3.8
